{"trial_id": "01", "hyperparameters": {"space": [{"class_name": "Int", "config": {"name": "lstm_units", "default": null, "conditions": [], "min_value": 32, "max_value": 128, "step": 32, "sampling": "linear"}}, {"class_name": "Float", "config": {"name": "lstm_dropout", "default": 0.0, "conditions": [], "min_value": 0.0, "max_value": 0.5, "step": 0.1, "sampling": "linear"}}, {"class_name": "Int", "config": {"name": "cnn_filters", "default": null, "conditions": [], "min_value": 32, "max_value": 128, "step": 32, "sampling": "linear"}}, {"class_name": "Float", "config": {"name": "cnn_dropout", "default": 0.0, "conditions": [], "min_value": 0.0, "max_value": 0.5, "step": 0.1, "sampling": "linear"}}], "values": {"lstm_units": 128, "lstm_dropout": 0.30000000000000004, "cnn_filters": 128, "cnn_dropout": 0.2}}, "metrics": {"metrics": {"loss": {"direction": "min", "observations": [{"value": [9579752.0], "step": 3}]}, "val_loss": {"direction": "min", "observations": [{"value": [10817882.5], "step": 3}]}}}, "score": 10817882.5, "best_step": 3, "status": "COMPLETED", "message": null}